tempcase/__init__.py
tempcase/cases.py
tempcase/version.py
tempcase-1.0.0.dist-info/LICENSE
tempcase-1.0.0.dist-info/METADATA
tempcase-1.0.0.dist-info/WHEEL
tempcase-1.0.0.dist-info/top_level.txt
tempcase-1.0.0.dist-info/RECORD
