Metadata-Version: 2.1
Name: tempcase
Version: 1.0.0
Summary: Utilities for handling python test cases with temporary directories and files, for people using `pyunit`/`unittest`.
Home-page: https://github.com/clbarnes/tempcase
Author: Chris L Barnes
Author-email: barnesc@janelia.hhmi.org
License: MIT
Keywords: test unittest pyunit tmp temp
Platform: UNKNOWN
Classifier: Development Status :: 4 - Beta
Classifier: License :: OSI Approved :: MIT License
Classifier: Programming Language :: Python
Classifier: Programming Language :: Python :: 3.6
Classifier: Programming Language :: Python :: 3.5
Classifier: Programming Language :: Python :: 3.4
Classifier: Programming Language :: Python :: 2.7
Requires-Python: >=2.7, !=3.0.*, !=3.1.*, !=3.2.*, !=3.3.*
Requires-Dist: backports.tempfile (>=1.0) ; python_version < "3.4"
